{
    "testing": {
        "avatar": {
            "low": 100000000,
            "high": 150000000
        },
        "living_abyss": {
            "low": 200000000,
            "high": 350000000
        },
        "dragon": {
            "low": 200000000,
            "high": 350000000
        }
    },
    "fall": {
        "avatar": {
            "low": 100000000,
            "high": 150000000
        },
        "living_abyss": {
            "low": 190000000,
            "high": 300000000
        },
        "dragon": {
            "low": 150000000,
            "high": 290000000
        }
    },
    "spring": {
        "avatar": {
            "low": 100000000,
            "high": 150000000
        },
        "living_abyss": {
            "low": 151000000,
            "high": 262000000
        },
        "dragon": {
            "low": 140000000,
            "high": 250000000
        }
    },
    "burnt": {
        "avatar": {
            "low": 100000000,
            "high": 150000000
        },
        "living_abyss": {
            "low": 200000000,
            "high": 300000000
        },
        "dragon": {
            "low": 200000000,
            "high": 360000000
        }
    },
    "royal": {
        "avatar": {
            "low": 100000000,
            "high": 150000000
        },
        "living_abyss": {
            "low": 100000000,
            "high": 300000000
        },
        "dragon": {
            "low": 120000000,
            "high": 280000000
        }
    },
    "other": {
        "avatar": {
            "low": 100000000,
            "high": 150000000
        },
        "living_abyss": {
            "low": 200000000,
            "high": 350000000
        },
        "dragon": {
            "low": 200000000,
            "high": 350000000
        }
    }
}